captchax-0.1.0.dist-info/METADATA
captchax-0.1.0.dist-info/WHEEL
captchax/__init__.py
captchax/captchax.cpython-311-s390x-linux-gnu.so
captchax-0.1.0.dist-info/RECORD
